CHANGELOG.md
report_E2E.md
shesha/__init__.py
shesha/ao/__init__.py
shesha/ao/basis.py
shesha/ao/cmats.py
shesha/ao/imats.py
shesha/ao/modopti.py
shesha/ao/tomo.py
shesha/ao/wfs.py
shesha/config/__init__.py
shesha/config/config_setter_utils.py
shesha/config/pAtmos.py
shesha/config/pCentroider.py
shesha/config/pConfig.py
shesha/config/pController.py
shesha/config/pCoronagraph.py
shesha/config/pDms.py
shesha/config/pGeom.py
shesha/config/pLoop.py
shesha/config/pTarget.py
shesha/config/pTel.py
shesha/config/pWfs.py
shesha/constants.py
shesha/init/__init__.py
shesha/init/atmos_init.py
shesha/init/coronagraph_init.py
shesha/init/dm_init.py
shesha/init/geom_init.py
shesha/init/lgs_init.py
shesha/init/rtc_init.py
shesha/init/target_init.py
shesha/init/wfs_init.py
shesha/scripts/__init__.py
shesha/scripts/closed_loop.py
shesha/scripts/dm_standalone.py
shesha/supervisor/__init__.py
shesha/supervisor/canapassSupervisor.py
shesha/supervisor/compassSupervisor.py
shesha/supervisor/components/__init__.py
shesha/supervisor/components/atmosCompass.py
shesha/supervisor/components/coronagraph/__init__.py
shesha/supervisor/components/coronagraph/coronagraphCompass.py
shesha/supervisor/components/coronagraph/genericCoronagraph.py
shesha/supervisor/components/coronagraph/perfectCoronagraph.py
shesha/supervisor/components/coronagraph/stellarCoronagraph.py
shesha/supervisor/components/dmCompass.py
shesha/supervisor/components/rtc/__init__.py
shesha/supervisor/components/rtc/rtcAbstract.py
shesha/supervisor/components/rtc/rtcCompass.py
shesha/supervisor/components/rtc/rtcStandalone.py
shesha/supervisor/components/sourceCompass.py
shesha/supervisor/components/targetCompass.py
shesha/supervisor/components/telescopeCompass.py
shesha/supervisor/components/wfsCompass.py
shesha/supervisor/genericSupervisor.py
shesha/supervisor/optimizers/__init__.py
shesha/supervisor/optimizers/calibration.py
shesha/supervisor/optimizers/modalBasis.py
shesha/supervisor/optimizers/modalGains.py
shesha-5.5.0.post2.dist-info/LICENSE
shesha-5.5.0.post2.dist-info/METADATA
shesha-5.5.0.post2.dist-info/WHEEL
shesha-5.5.0.post2.dist-info/RECORD
