Metadata-Version: 2.1
Name: shesha
Version: 5.5.0.post2
Summary: SHESHA is the python part of the COMPASS platform designed to meet the need of high-performance for the simulation of AO systems
Home-page: https://github.com/ANR-COMPASS/shesha
License: LGPL-3.0-or-later
Author: Florian Ferreira
Author-email: florian.ferreira@obspm.fr
Maintainer: Florian Ferreira
Maintainer-email: florian.ferreira@obspm.fr
Requires-Python: >=3.9,<4.0
Classifier: License :: OSI Approved :: GNU Lesser General Public License v3 or later (LGPLv3+)
Classifier: Programming Language :: Python :: 3
Classifier: Programming Language :: Python :: 3.9
Classifier: Programming Language :: Python :: 3.10
Classifier: Programming Language :: Python :: 3.11
Classifier: Programming Language :: Python :: 3.12
Requires-Dist: astropy (>=6.0.0,<7.0.0)
Requires-Dist: docopt (>=0.6.2,<0.7.0)
Requires-Dist: h5py (>=3.10.0,<4.0.0)
Requires-Dist: ipython (>=8.18.1,<9.0.0)
Requires-Dist: matplotlib (>=3.8.2,<4.0.0)
Requires-Dist: numpy (>=1.26.2,<2.0.0)
Requires-Dist: packaging (>=23.2,<24.0)
Requires-Dist: pandas (>=2.1.4,<3.0.0)
Requires-Dist: pyqtgraph (>=0.13.3,<0.14.0)
Requires-Dist: rich (>=13.7.0,<14.0.0)
Requires-Dist: scipy (>=1.11.4,<2.0.0)
Requires-Dist: tables (>=3.9.2,<4.0.0)
Requires-Dist: tabulate (>=0.9.0,<0.10.0)
Project-URL: Documentation, https://shesha.readthedocs.io/en/master/
Project-URL: Repository, https://github.com/ANR-COMPASS/shesha
